download.py
download_tarball-0.0.7.dist-info/LICENSE
download_tarball-0.0.7.dist-info/METADATA
download_tarball-0.0.7.dist-info/WHEEL
download_tarball-0.0.7.dist-info/entry_points.txt
download_tarball-0.0.7.dist-info/top_level.txt
download_tarball-0.0.7.dist-info/RECORD
