Metadata-Version: 2.1
Name: download-tarball
Version: 0.0.7
Summary: Automates manual installation of Python modules.
Home-page: https://github.com/OpticGenius/download-tarball
Author: Armaan McLeod
Author-email: opticgenius@hotmail.com
License: UNKNOWN
Project-URL: Bug Reports, https://github.com/OpticGenius/download-tarball/issues
Project-URL: Source, https://github.com/OpticGenius/download-tarball
Keywords: python tarball download
Platform: UNKNOWN
Classifier: Development Status :: 5 - Production/Stable
Classifier: Intended Audience :: Developers
Classifier: Topic :: Software Development :: Build Tools
Classifier: License :: OSI Approved :: MIT License
Classifier: Programming Language :: Python :: 3
Classifier: Programming Language :: Python :: 3.4
Classifier: Programming Language :: Python :: 3.5
Classifier: Programming Language :: Python :: 3.6
Classifier: Programming Language :: Python :: 3.7
Requires-Dist: tqdm
Requires-Dist: requests
Requires-Dist: beautifulsoup4
